LICENSE
MANIFEST.in
README.md
setup.py
youhi/Button.py
youhi/MenuTrigger.py
youhi/Youhi.py
youhi/__init__.py
youhi/_imports_.py
youhi/metadata.json
youhi/package.json
youhi/style.css
youhi/youhi.js
youhi.egg-info/PKG-INFO
youhi.egg-info/SOURCES.txt
youhi.egg-info/dependency_links.txt
youhi.egg-info/top_level.txt