Metadata-Version: 2.1
Name: youhi
Version: 1.0.7
Summary: Plotly dash React component UI library boilerplate
Home-page: UNKNOWN
Author: thesameeric <osivwiokiti@gmail.com>
License: MIT
Platform: UNKNOWN
Classifier: Framework :: Dash
License-File: LICENSE
